ionoscloud_logging/__init__.py
ionoscloud_logging/api_client.py
ionoscloud_logging/api_response.py
ionoscloud_logging/configuration.py
ionoscloud_logging/exceptions.py
ionoscloud_logging/rest.py
ionoscloud_logging/test-driver.py
ionoscloud_logging/api/__init__.py
ionoscloud_logging/api/pipelines_api.py
ionoscloud_logging/models/__init__.py
ionoscloud_logging/models/create_request.py
ionoscloud_logging/models/create_request_pipeline.py
ionoscloud_logging/models/create_request_properties.py
ionoscloud_logging/models/destination.py
ionoscloud_logging/models/error_message.py
ionoscloud_logging/models/error_response.py
ionoscloud_logging/models/metadata.py
ionoscloud_logging/models/patch_request.py
ionoscloud_logging/models/patch_request_pipeline.py
ionoscloud_logging/models/patch_request_properties.py
ionoscloud_logging/models/pipeline.py
ionoscloud_logging/models/pipeline_create.py
ionoscloud_logging/models/pipeline_create_properties.py
ionoscloud_logging/models/pipeline_create_properties_logs.py
ionoscloud_logging/models/pipeline_key200_response.py
ionoscloud_logging/models/pipeline_list_response.py
ionoscloud_logging/models/pipeline_patch.py
ionoscloud_logging/models/pipeline_patch_properties.py
ionoscloud_logging/models/pipeline_properties.py
ionoscloud_logging/models/pipeline_response.py
ionoscloud_logging/models/pipeline_response_all_of.py
ionoscloud_logging/models/pipeline_response_all_of1.py
ionoscloud_logging/models/pipelines_key_post200_response.py
ionoscloud_logging/models/processor.py
ionoscloud_logging/models/response_pipeline.py
ionoscloud_logging/models/response_pipeline_all_of.py
ionoscloud_logging/models/response_pipeline_all_of1.py
ionoscloud_logging-1.0.0.dist-info/LICENSE
ionoscloud_logging-1.0.0.dist-info/METADATA
ionoscloud_logging-1.0.0.dist-info/WHEEL
ionoscloud_logging-1.0.0.dist-info/top_level.txt
ionoscloud_logging-1.0.0.dist-info/RECORD
